alert_msgs/__init__.py
alert_msgs/alerts.py
alert_msgs/components.py
alert_msgs/discord.py
alert_msgs/emails.py
alert_msgs/report.py
alert_msgs/slack.py
alert_msgs/utils.py
alert_msgs-0.8.1.dist-info/METADATA
alert_msgs-0.8.1.dist-info/WHEEL
alert_msgs-0.8.1.dist-info/RECORD
