Metadata-Version: 2.4
Name: alert-msgs
Version: 0.8.1
Summary: 
Author: Dan Kelleher
Author-email: kelleherjdan@gmail.com
Requires-Python: >=3.12
Classifier: Programming Language :: Python :: 3
Classifier: Programming Language :: Python :: 3.12
Classifier: Programming Language :: Python :: 3.13
Classifier: Programming Language :: Python :: 3.14
Requires-Dist: aiohttp (>=3.12.15,<4.0.0)
Requires-Dist: aiosmtplib (>=4.0.1,<5.0.0)
Requires-Dist: async-lru (>=2.0.5,<3.0.0)
Requires-Dist: dominate (>=2.9.1,<3.0.0)
Requires-Dist: emoji (>=2.14.1,<3.0.0)
Requires-Dist: imgkit (>=1.2.3,<2.0.0)
Requires-Dist: loguru (>=0.7.2,<1.0.0)
Requires-Dist: premailer (>=3.10.0,<4.0.0)
Requires-Dist: prettytable (>=3.16.0,<4.0.0)
Requires-Dist: pydantic (>=2.11.7,<3.0.0)
Requires-Dist: pydantic-settings (>=2.10.1,<3.0.0)
Requires-Dist: rich (>=14.1.0,<15.0.0)
Requires-Dist: slack-sdk (>=3.36.0,<4.0.0)
Requires-Dist: toolz (>=1.0.0,<2.0.0)
Requires-Dist: xxhash (>=3.5.0,<4.0.0)
